{
  "type_description_msg": {
    "type_description": {
      "type_name": "rmf_building_map_msgs/msg/GraphNode",
      "fields": [
        {
          "name": "x",
          "type": {
            "type_id": 10,
            "capacity": 0,
            "string_capacity": 0,
            "nested_type_name": ""
          },
          "default_value": ""
        },
        {
          "name": "y",
          "type": {
            "type_id": 10,
            "capacity": 0,
            "string_capacity": 0,
            "nested_type_name": ""
          },
          "default_value": ""
        },
        {
          "name": "name",
          "type": {
            "type_id": 17,
            "capacity": 0,
            "string_capacity": 0,
            "nested_type_name": ""
          },
          "default_value": ""
        },
        {
          "name": "params",
          "type": {
            "type_id": 145,
            "capacity": 0,
            "string_capacity": 0,
            "nested_type_name": "rmf_building_map_msgs/msg/Param"
          },
          "default_value": ""
        }
      ]
    },
    "referenced_type_descriptions": [
      {
        "type_name": "rmf_building_map_msgs/msg/Param",
        "fields": [
          {
            "name": "name",
            "type": {
              "type_id": 17,
              "capacity": 0,
              "string_capacity": 0,
              "nested_type_name": ""
            },
            "default_value": ""
          },
          {
            "name": "type",
            "type": {
              "type_id": 7,
              "capacity": 0,
              "string_capacity": 0,
              "nested_type_name": ""
            },
            "default_value": ""
          },
          {
            "name": "value_int",
            "type": {
              "type_id": 6,
              "capacity": 0,
              "string_capacity": 0,
              "nested_type_name": ""
            },
            "default_value": ""
          },
          {
            "name": "value_float",
            "type": {
              "type_id": 10,
              "capacity": 0,
              "string_capacity": 0,
              "nested_type_name": ""
            },
            "default_value": ""
          },
          {
            "name": "value_string",
            "type": {
              "type_id": 17,
              "capacity": 0,
              "string_capacity": 0,
              "nested_type_name": ""
            },
            "default_value": ""
          },
          {
            "name": "value_bool",
            "type": {
              "type_id": 15,
              "capacity": 0,
              "string_capacity": 0,
              "nested_type_name": ""
            },
            "default_value": ""
          }
        ]
      }
    ]
  },
  "type_hashes": [
    {
      "type_name": "rmf_building_map_msgs/msg/GraphNode",
      "hash_string": "RIHS01_cd8d66c032b19ee08cd2506638f4f613410d77c4f885006695f5d42b8e7138af"
    },
    {
      "type_name": "rmf_building_map_msgs/msg/Param",
      "hash_string": "RIHS01_a72579778c6d0c56ef07b62664e5a8b1a94c0d742fd865b65dcb40472b140a59"
    }
  ]
}